autograde/__init__.py
autograde/__main__.py
autograde/helpers.py
autograde/notebook_executor.py
autograde/notebook_test.py
autograde/test_result.py
autograde/util.py
autograde/cli/__init__.py
autograde/cli/__main__.py
autograde/cli/audit.py
autograde/cli/build.py
autograde/cli/patch.py
autograde/cli/report.py
autograde/cli/summary.py
autograde/cli/test.py
autograde/cli/util.py
autograde/cli/version.py
autograde/static/__init__.py
autograde/static/basic.css
autograde/static/favicon.ico
autograde/static/inject_after.py
autograde/static/inject_before.py
autograde/templates/audit.html
autograde/templates/base.html
autograde/templates/error.html
autograde/templates/message.html
autograde/templates/report.html
autograde/templates/results.html
autograde/templates/summary.html
autograde_test/__init__.py
autograde_test/test___main__.py
autograde_test/test_helpers.py
autograde_test/test_notebook_executor.py
autograde_test/test_notebook_test.py
autograde_test/test_test_result.py
autograde_test/test_util.py
autograde_test/util.py
jupyter_autograde-0.2.4.dist-info/LICENSE
jupyter_autograde-0.2.4.dist-info/METADATA
jupyter_autograde-0.2.4.dist-info/WHEEL
jupyter_autograde-0.2.4.dist-info/entry_points.txt
jupyter_autograde-0.2.4.dist-info/top_level.txt
jupyter_autograde-0.2.4.dist-info/RECORD
