Metadata-Version: 2.1
Name: jupyter-autograde
Version: 0.2.4
Summary: automatic grading of jupyter notebooks
Home-page: https://github.com/cssh-rwth/autograde
Author: 0b11001111
Maintainer: Chair for Computational Social Sciences and Humanities at RWTH Aachen University
Maintainer-email: admin@cssh.rwth-aachen.de
License: MIT
Keywords: jupyter,teaching,unit test
Platform: UNKNOWN
Classifier: Natural Language :: English
Classifier: Programming Language :: Python
Classifier: Operating System :: OS Independent
Requires-Python: >=3.8
Requires-Dist: dataclasses-json
Requires-Dist: numpy
Requires-Dist: scipy
Requires-Dist: pandas
Requires-Dist: matplotlib
Requires-Dist: seaborn
Requires-Dist: ipykernel
Requires-Dist: jupyter
Requires-Dist: jinja2
Requires-Dist: flask
Requires-Dist: pytz
Requires-Dist: django-htmlmin
Provides-Extra: develop
Requires-Dist: nose ; extra == 'develop'
Requires-Dist: setuptools ; extra == 'develop'
Requires-Dist: wheel ; extra == 'develop'
Requires-Dist: twine ; extra == 'develop'
Requires-Dist: flake8 ; extra == 'develop'
